pypnm_cmts/__init__.py
pypnm_cmts/__main__.py
pypnm_cmts/cli.py
pypnm_cmts/combined_mode.py
pypnm_cmts/py.typed
pypnm_cmts/version.py
pypnm_cmts/api/__init__.py
pypnm_cmts/api/main.py
pypnm_cmts/api/common/__init__.py
pypnm_cmts/api/common/cmts_reg_status.py
pypnm_cmts/api/common/cmts_request.py
pypnm_cmts/api/common/cm/schema.py
pypnm_cmts/api/common/cmts/schema.py
pypnm_cmts/api/common/service/__init__.py
pypnm_cmts/api/common/service/status_codes.py
pypnm_cmts/api/routes/__init__.py
pypnm_cmts/api/routes/common/__init__.py
pypnm_cmts/api/routes/common/service/__init__.py
pypnm_cmts/api/routes/common/service/status_codes.py
pypnm_cmts/api/routes/operational/__init__.py
pypnm_cmts/api/routes/operational/router.py
pypnm_cmts/api/routes/operational/schemas.py
pypnm_cmts/api/routes/operational/service.py
pypnm_cmts/api/routes/orchestrator/__init__.py
pypnm_cmts/api/routes/orchestrator/router.py
pypnm_cmts/api/routes/orchestrator/schemas.py
pypnm_cmts/api/routes/serving_group/__init__.py
pypnm_cmts/api/routes/serving_group/router.py
pypnm_cmts/api/routes/serving_group/schemas.py
pypnm_cmts/api/routes/serving_group/service.py
pypnm_cmts/api/routes/system/__init__.py
pypnm_cmts/api/routes/system/router.py
pypnm_cmts/api/routes/system/schemas.py
pypnm_cmts/api/routes/system/service.py
pypnm_cmts/api/utils/__init__.py
pypnm_cmts/api/utils/auto_load.py
pypnm_cmts/cmts/__init__.py
pypnm_cmts/cmts/channel_inventory_collector.py
pypnm_cmts/cmts/discovery_models.py
pypnm_cmts/cmts/inventory_discovery.py
pypnm_cmts/cmts/service_group_topology_collector.py
pypnm_cmts/cmts/adapters/__init__.py
pypnm_cmts/cmts/adapters/base.py
pypnm_cmts/cmts/adapters/snmp_adapter.py
pypnm_cmts/config/__init__.py
pypnm_cmts/config/config_manager.py
pypnm_cmts/config/log_config.py
pypnm_cmts/config/orchestrator_config.py
pypnm_cmts/config/owner_id_resolver.py
pypnm_cmts/config/pnm_config_manager.py
pypnm_cmts/config/request_defaults.py
pypnm_cmts/config/system_config_settings.py
pypnm_docsis_cmts-0.1.44.0.dist-info/licenses/LICENSE
pypnm_docsis_cmts-0.1.44.0.dist-info/licenses/NOTICE
pypnm_docsis_cmts-0.1.44.0.dist-info/METADATA
pypnm_docsis_cmts-0.1.44.0.dist-info/WHEEL
pypnm_docsis_cmts-0.1.44.0.dist-info/entry_points.txt
pypnm_docsis_cmts-0.1.44.0.dist-info/top_level.txt
pypnm_docsis_cmts-0.1.44.0.dist-info/RECORD
