Metadata-Version: 2.4
Name: pypnm-docsis-cmts
Version: 0.1.44.0
Summary: DOCSIS CMTS tools built on the PyPNM toolkit
Author-email: Maurice Garcia <mgarcia01752@outlook.com>
License-Expression: Apache-2.0
Project-URL: Homepage, https://www.pypnm.io
Project-URL: Repository, https://github.com/PyPNMApps/PyPNM-CMTS
Project-URL: Bug-Tracker, https://github.com/PyPNMApps/PyPNM-CMTS/issues
Classifier: Programming Language :: Python :: 3
Classifier: Programming Language :: Python :: 3 :: Only
Classifier: Programming Language :: Python :: 3.10
Classifier: Programming Language :: Python :: 3.11
Classifier: Programming Language :: Python :: 3.12
Classifier: Programming Language :: Python :: 3.13
Classifier: Operating System :: OS Independent
Classifier: Topic :: System :: Networking
Classifier: Typing :: Typed
Requires-Python: >=3.10
License-File: LICENSE
License-File: NOTICE
Requires-Dist: pypnm-docsis>=1.0.13.0
Provides-Extra: dev
Requires-Dist: ruff>=0.6.9; extra == "dev"
Requires-Dist: pytest>=8.0.0; extra == "dev"
Requires-Dist: pytest-asyncio>=0.23.5; extra == "dev"
Requires-Dist: httpx<0.28.0,>=0.27.0; extra == "dev"
Requires-Dist: build>=1.2.0; extra == "dev"
Requires-Dist: twine>=5.0.0; extra == "dev"
Provides-Extra: test
Requires-Dist: pytest>=8.0.0; extra == "test"
Requires-Dist: pytest-asyncio>=0.23.5; extra == "test"
Requires-Dist: httpx<0.28.0,>=0.27.0; extra == "test"
Requires-Dist: build>=1.2.0; extra == "test"
Requires-Dist: twine>=5.0.0; extra == "test"
Provides-Extra: docs
Requires-Dist: mkdocs>=1.5.0; extra == "docs"
Requires-Dist: mkdocs-material>=9.0.0; extra == "docs"
Requires-Dist: mkdocs-mermaid2-plugin>=1.1.1; extra == "docs"
Requires-Dist: pymdown-extensions>=10.0.0; extra == "docs"
Dynamic: license-file
